shinymedia/__init__.py
shinymedia/ui.py
shinymedia/dist/index.css
shinymedia/dist/index.js
shinymedia-0.1.1.dist-info/LICENSE
shinymedia-0.1.1.dist-info/METADATA
shinymedia-0.1.1.dist-info/WHEEL
shinymedia-0.1.1.dist-info/top_level.txt
shinymedia-0.1.1.dist-info/RECORD
