Metadata-Version: 2.1
Name: shinymedia
Version: 0.1.1
Summary: Extends the Shiny web framework with controls for multimedia input/output.
Author-email: Joe Cheng <joe@posit.co>
License: Copyright 2024 Posit Software, PBC
Project-URL: homepage, https://github.com/posit-dev/shinymedia
Project-URL: documentation, https://posit-dev.github.io/shinymedia/
Keywords: video,audio,shiny
Classifier: Intended Audience :: Developers
Classifier: License :: OSI Approved :: MIT License
Classifier: Programming Language :: Python
Classifier: Programming Language :: Python :: 3.9
Classifier: Programming Language :: Python :: 3.10
Classifier: Programming Language :: Python :: 3.11
Classifier: Programming Language :: Python :: 3.12
Classifier: Topic :: Internet :: WWW/HTTP :: Dynamic Content
Classifier: Topic :: Software Development :: Libraries :: Python Modules
Classifier: Topic :: Text Processing :: Markup :: HTML
Classifier: Topic :: Scientific/Engineering :: Visualization
Requires-Python: >=3.9
License-File: LICENSE
Requires-Dist: faicons
Requires-Dist: htmltools
Requires-Dist: shiny
Provides-Extra: dev
Requires-Dist: black ; extra == 'dev'
Requires-Dist: flake8 ; extra == 'dev'
Requires-Dist: isort ; extra == 'dev'
Requires-Dist: wheel ; extra == 'dev'
Provides-Extra: docs
Requires-Dist: jupyter ; extra == 'docs'
Requires-Dist: quartodoc ; extra == 'docs'
